{
  "trace_schema": "paper_bpc_core_plateau_trace_v1",
  "trace_scope": "frontier_interval_ledger_with_available_aggregate_tree_and_pricing_stats",
  "instance_name": "moderate_seed3301.txt",
  "input_path": "E:\\codes\\ExactEBRP\\reference\\hard_stress\\V20_M3\\moderate_seed3301.txt",
  "algorithm_preset": "paper-gf-tailored-bc",
  "method": "gcap-frontier",
  "status": "gcap_frontier_not_closed",
  "objective": 0.0491525526647,
  "lower_bound": 0.0122881381662,
  "upper_bound": 0.0491525526647,
  "gap": 0.75,
  "certified_original_problem": false,
  "full_certificate_rejection_reason": "unresolved_intervals",
  "runtime_breakdown": {"bound_time_seconds": 597.409032, "route_mask_time_seconds": 0, "master_time_seconds": 0.3129767, "pricing_time_seconds": 9204.003921},
  "controlling_interval": {"id": 18, "range": "[0.0122881,0.0123841]", "lower_bound": 0.0122881381662, "source": "gamma_floor"},
  "branch_price_node_trace_available": true,
  "branch_price_node_trace_limitation": "node trace is available for branch-price trees that actually started in this run",
  "aggregate_tree": {"nodes": 1, "open_nodes": 10, "pricing_closed_nodes": 0, "columns": 4620, "cuts_added": 0},
  "pricing_call_trace_available": true,
  "pricing_call_trace_limitation": "pricing call trace is available for branch-price nodes that actually started in this run",
  "aggregate_pricing": {"pricing_calls": 1, "pricing_completed_exactly": false, "pricing_closure_certified_exact": false, "pricing_closure_status": "pricing_time_limit", "pricing_best_reduced_cost_any": 0.00182087521921, "pricing_remaining_negative_rc": 0, "duplicate_negative_projections": 0, "blocked_by_duplicate_projection": false, "completion_lb_pruned_labels": 0, "required_closure_pruned_labels": 0, "label_dominance_comparisons": 0, "label_dominance_pruned_labels": 0, "label_dominance_cross_pickup_pruned_labels": 0, "label_dominance_inactive_entries_skipped": 0, "label_dominance_bucket_compactions": 0, "label_dominance_compacted_entries": 0, "operation_dp_dominance_pruned_states": 4696761045},
  "interval_trace_csv": "E:\\codes\\ExactEBRP\\results\\gf_tailored_bc_route_profile_full_frontier_round\\raw\\moderate_seed3301_tailored_14400s.intervals.csv",
  "intervals": [
    {"interval_id": 0, "gamma_L": 0, "gamma_U": 0.0122881381662, "current_interval_lower_bound": 0, "incumbent_upper_bound": 0.0491525526647, "status": "replaced_by_children", "reason": "split_parent_replaced", "certificate_basis": "unresolved", "requires_pricing_closure": false, "pricing_closure_available": false, "interval_bound_valid": true, "bpc_nodes": 0, "open_nodes": 1, "generated_columns": 0, "cuts": 0, "pricing_calls": 0, "pricing_time_seconds": 0, "rmp_solve_time_seconds": 0, "relaxation_time_seconds": 30.5637516, "lower_bound_source": "gamma_floor", "lower_bound_sources": "gamma_floor"},
    {"interval_id": 1, "gamma_L": 0.0122881381662, "gamma_U": 0.0245762763324, "current_interval_lower_bound": 0.0122881381662, "incumbent_upper_bound": 0.0491525526647, "status": "replaced_by_children", "reason": "split_parent_replaced", "certificate_basis": "unresolved", "requires_pricing_closure": false, "pricing_closure_available": false, "interval_bound_valid": true, "bpc_nodes": 0, "open_nodes": 1, "generated_columns": 0, "cuts": 0, "pricing_calls": 0, "pricing_time_seconds": 0, "rmp_solve_time_seconds": 0, "relaxation_time_seconds": 30.2367068, "lower_bound_source": "gamma_floor", "lower_bound_sources": "gamma_floor"},
    {"interval_id": 2, "gamma_L": 0.0245762763324, "gamma_U": 0.0368644144986, "current_interval_lower_bound": 0.0245762763324, "incumbent_upper_bound": 0.0491525526647, "status": "unresolved", "reason": "tree_not_started_before_time_limit_or_reserve", "certificate_basis": "unresolved", "requires_pricing_closure": false, "pricing_closure_available": false, "interval_bound_valid": true, "bpc_nodes": 0, "open_nodes": 1, "generated_columns": 0, "cuts": 0, "pricing_calls": 0, "pricing_time_seconds": 0, "rmp_solve_time_seconds": 0, "relaxation_time_seconds": 29.9978285, "lower_bound_source": "gamma_floor", "lower_bound_sources": "gamma_floor"},
    {"interval_id": 3, "gamma_L": 0.0368644144986, "gamma_U": 0.0491525526647, "current_interval_lower_bound": 0.0368644144986, "incumbent_upper_bound": 0.0491525526647, "status": "unresolved", "reason": "tree_not_started_before_time_limit_or_reserve", "certificate_basis": "unresolved", "requires_pricing_closure": false, "pricing_closure_available": false, "interval_bound_valid": true, "bpc_nodes": 0, "open_nodes": 1, "generated_columns": 0, "cuts": 0, "pricing_calls": 0, "pricing_time_seconds": 0, "rmp_solve_time_seconds": 0, "relaxation_time_seconds": 29.8042871, "lower_bound_source": "gamma_floor", "lower_bound_sources": "gamma_floor"},
    {"interval_id": 4, "gamma_L": 0, "gamma_U": 0.00614406908309, "current_interval_lower_bound": 0.0491525526647, "incumbent_upper_bound": 0.0491525526647, "status": "bound_fathomed", "reason": "inventory_route_gini_relaxation", "certificate_basis": "inventory_route_gini_relaxation_fathomed", "requires_pricing_closure": false, "pricing_closure_available": false, "interval_bound_valid": true, "bpc_nodes": 0, "open_nodes": 0, "generated_columns": 0, "cuts": 0, "pricing_calls": 0, "pricing_time_seconds": 0, "rmp_solve_time_seconds": 0, "relaxation_time_seconds": 10.5009512, "lower_bound_source": "inventory_route_gini_relaxation", "lower_bound_sources": "gamma_floor|inventory_route_gini_relaxation"},
    {"interval_id": 5, "gamma_L": 0.00614406908309, "gamma_U": 0.0122881381662, "current_interval_lower_bound": 0.0491525526647, "incumbent_upper_bound": 0.0491525526647, "status": "bound_fathomed", "reason": "inventory_route_gini_relaxation", "certificate_basis": "inventory_route_gini_relaxation_fathomed", "requires_pricing_closure": false, "pricing_closure_available": false, "interval_bound_valid": true, "bpc_nodes": 0, "open_nodes": 0, "generated_columns": 0, "cuts": 0, "pricing_calls": 0, "pricing_time_seconds": 0, "rmp_solve_time_seconds": 0, "relaxation_time_seconds": 15.1384512, "lower_bound_source": "inventory_route_gini_relaxation", "lower_bound_sources": "gamma_floor|inventory_route_gini_relaxation"},
    {"interval_id": 6, "gamma_L": 0.0122881381662, "gamma_U": 0.0184322072493, "current_interval_lower_bound": 0.0122881381662, "incumbent_upper_bound": 0.0491525526647, "status": "replaced_by_children", "reason": "split_parent_replaced", "certificate_basis": "unresolved", "requires_pricing_closure": false, "pricing_closure_available": false, "interval_bound_valid": true, "bpc_nodes": 0, "open_nodes": 1, "generated_columns": 0, "cuts": 0, "pricing_calls": 0, "pricing_time_seconds": 0, "rmp_solve_time_seconds": 0, "relaxation_time_seconds": 30.1508106, "lower_bound_source": "gamma_floor", "lower_bound_sources": "gamma_floor"},
    {"interval_id": 7, "gamma_L": 0.0184322072493, "gamma_U": 0.0245762763324, "current_interval_lower_bound": 0.0184322072493, "incumbent_upper_bound": 0.0491525526647, "status": "unresolved", "reason": "tree_not_started_before_time_limit_or_reserve", "certificate_basis": "unresolved", "requires_pricing_closure": false, "pricing_closure_available": false, "interval_bound_valid": true, "bpc_nodes": 0, "open_nodes": 1, "generated_columns": 0, "cuts": 0, "pricing_calls": 0, "pricing_time_seconds": 0, "rmp_solve_time_seconds": 0, "relaxation_time_seconds": 30.0219846, "lower_bound_source": "gamma_floor", "lower_bound_sources": "gamma_floor"},
    {"interval_id": 8, "gamma_L": 0.0122881381662, "gamma_U": 0.0153601727077, "current_interval_lower_bound": 0.0122881381662, "incumbent_upper_bound": 0.0491525526647, "status": "replaced_by_children", "reason": "split_parent_replaced", "certificate_basis": "unresolved", "requires_pricing_closure": false, "pricing_closure_available": false, "interval_bound_valid": true, "bpc_nodes": 0, "open_nodes": 1, "generated_columns": 0, "cuts": 0, "pricing_calls": 0, "pricing_time_seconds": 0, "rmp_solve_time_seconds": 0, "relaxation_time_seconds": 30.1631456, "lower_bound_source": "gamma_floor", "lower_bound_sources": "gamma_floor"},
    {"interval_id": 9, "gamma_L": 0.0153601727077, "gamma_U": 0.0184322072493, "current_interval_lower_bound": 0.0153601727077, "incumbent_upper_bound": 0.0491525526647, "status": "unresolved", "reason": "tree_not_started_before_time_limit_or_reserve", "certificate_basis": "unresolved", "requires_pricing_closure": false, "pricing_closure_available": false, "interval_bound_valid": true, "bpc_nodes": 0, "open_nodes": 1, "generated_columns": 0, "cuts": 0, "pricing_calls": 0, "pricing_time_seconds": 0, "rmp_solve_time_seconds": 0, "relaxation_time_seconds": 30.1418342, "lower_bound_source": "gamma_floor", "lower_bound_sources": "gamma_floor"},
    {"interval_id": 10, "gamma_L": 0.0122881381662, "gamma_U": 0.013824155437, "current_interval_lower_bound": 0.0122881381662, "incumbent_upper_bound": 0.0491525526647, "status": "replaced_by_children", "reason": "split_parent_replaced", "certificate_basis": "unresolved", "requires_pricing_closure": false, "pricing_closure_available": false, "interval_bound_valid": true, "bpc_nodes": 0, "open_nodes": 1, "generated_columns": 0, "cuts": 0, "pricing_calls": 0, "pricing_time_seconds": 0, "rmp_solve_time_seconds": 0, "relaxation_time_seconds": 30.127532, "lower_bound_source": "gamma_floor", "lower_bound_sources": "gamma_floor"},
    {"interval_id": 11, "gamma_L": 0.013824155437, "gamma_U": 0.0153601727077, "current_interval_lower_bound": 0.013824155437, "incumbent_upper_bound": 0.0491525526647, "status": "unresolved", "reason": "tree_not_started_before_time_limit_or_reserve", "certificate_basis": "unresolved", "requires_pricing_closure": false, "pricing_closure_available": false, "interval_bound_valid": true, "bpc_nodes": 0, "open_nodes": 1, "generated_columns": 0, "cuts": 0, "pricing_calls": 0, "pricing_time_seconds": 0, "rmp_solve_time_seconds": 0, "relaxation_time_seconds": 30.107647, "lower_bound_source": "gamma_floor", "lower_bound_sources": "gamma_floor"},
    {"interval_id": 12, "gamma_L": 0.0122881381662, "gamma_U": 0.0130561468016, "current_interval_lower_bound": 0.0122881381662, "incumbent_upper_bound": 0.0491525526647, "status": "replaced_by_children", "reason": "split_parent_replaced", "certificate_basis": "unresolved", "requires_pricing_closure": false, "pricing_closure_available": false, "interval_bound_valid": true, "bpc_nodes": 0, "open_nodes": 1, "generated_columns": 0, "cuts": 0, "pricing_calls": 0, "pricing_time_seconds": 0, "rmp_solve_time_seconds": 0, "relaxation_time_seconds": 30.0687933, "lower_bound_source": "gamma_floor", "lower_bound_sources": "gamma_floor"},
    {"interval_id": 13, "gamma_L": 0.0130561468016, "gamma_U": 0.013824155437, "current_interval_lower_bound": 0.0130561468016, "incumbent_upper_bound": 0.0491525526647, "status": "unresolved", "reason": "tree_not_started_before_time_limit_or_reserve", "certificate_basis": "unresolved", "requires_pricing_closure": false, "pricing_closure_available": false, "interval_bound_valid": true, "bpc_nodes": 0, "open_nodes": 1, "generated_columns": 0, "cuts": 0, "pricing_calls": 0, "pricing_time_seconds": 0, "rmp_solve_time_seconds": 0, "relaxation_time_seconds": 30.1022222, "lower_bound_source": "gamma_floor", "lower_bound_sources": "gamma_floor"},
    {"interval_id": 14, "gamma_L": 0.0122881381662, "gamma_U": 0.0126721424839, "current_interval_lower_bound": 0.0122881381662, "incumbent_upper_bound": 0.0491525526647, "status": "replaced_by_children", "reason": "split_parent_replaced", "certificate_basis": "unresolved", "requires_pricing_closure": false, "pricing_closure_available": false, "interval_bound_valid": true, "bpc_nodes": 0, "open_nodes": 1, "generated_columns": 0, "cuts": 0, "pricing_calls": 0, "pricing_time_seconds": 0, "rmp_solve_time_seconds": 0, "relaxation_time_seconds": 30.0624078, "lower_bound_source": "gamma_floor", "lower_bound_sources": "gamma_floor"},
    {"interval_id": 15, "gamma_L": 0.0126721424839, "gamma_U": 0.0130561468016, "current_interval_lower_bound": 0.0126721424839, "incumbent_upper_bound": 0.0491525526647, "status": "unresolved", "reason": "tree_not_started_before_time_limit_or_reserve", "certificate_basis": "unresolved", "requires_pricing_closure": false, "pricing_closure_available": false, "interval_bound_valid": true, "bpc_nodes": 0, "open_nodes": 1, "generated_columns": 0, "cuts": 0, "pricing_calls": 0, "pricing_time_seconds": 0, "rmp_solve_time_seconds": 0, "relaxation_time_seconds": 30.01422, "lower_bound_source": "gamma_floor", "lower_bound_sources": "gamma_floor"},
    {"interval_id": 16, "gamma_L": 0.0122881381662, "gamma_U": 0.012480140325, "current_interval_lower_bound": 0.0122881381662, "incumbent_upper_bound": 0.0491525526647, "status": "replaced_by_children", "reason": "split_parent_replaced", "certificate_basis": "unresolved", "requires_pricing_closure": false, "pricing_closure_available": false, "interval_bound_valid": true, "bpc_nodes": 0, "open_nodes": 1, "generated_columns": 0, "cuts": 0, "pricing_calls": 0, "pricing_time_seconds": 0, "rmp_solve_time_seconds": 0, "relaxation_time_seconds": 30.0791989, "lower_bound_source": "gamma_floor", "lower_bound_sources": "gamma_floor"},
    {"interval_id": 17, "gamma_L": 0.012480140325, "gamma_U": 0.0126721424839, "current_interval_lower_bound": 0.012480140325, "incumbent_upper_bound": 0.0491525526647, "status": "unresolved", "reason": "tree_not_started_before_time_limit_or_reserve", "certificate_basis": "unresolved", "requires_pricing_closure": false, "pricing_closure_available": false, "interval_bound_valid": true, "bpc_nodes": 0, "open_nodes": 1, "generated_columns": 0, "cuts": 0, "pricing_calls": 0, "pricing_time_seconds": 0, "rmp_solve_time_seconds": 0, "relaxation_time_seconds": 30.0725242, "lower_bound_source": "gamma_floor", "lower_bound_sources": "gamma_floor"},
    {"interval_id": 18, "gamma_L": 0.0122881381662, "gamma_U": 0.0123841392456, "current_interval_lower_bound": 0.0122881381662, "incumbent_upper_bound": 0.0491525526647, "status": "unresolved", "reason": "open_bpc_nodes", "certificate_basis": "unresolved", "requires_pricing_closure": false, "pricing_closure_available": false, "interval_bound_valid": true, "bpc_nodes": 1, "open_nodes": 1, "generated_columns": 4620, "cuts": 0, "pricing_calls": 1, "pricing_time_seconds": 9204.003921, "rmp_solve_time_seconds": 0.3129767, "relaxation_time_seconds": 60.0676736, "lower_bound_source": "gamma_floor", "lower_bound_sources": "gamma_floor|branch_price_tree"},
    {"interval_id": 19, "gamma_L": 0.0123841392456, "gamma_U": 0.012480140325, "current_interval_lower_bound": 0.0123841392456, "incumbent_upper_bound": 0.0491525526647, "status": "unresolved", "reason": "tree_not_started_before_time_limit_or_reserve", "certificate_basis": "unresolved", "requires_pricing_closure": false, "pricing_closure_available": false, "interval_bound_valid": true, "bpc_nodes": 0, "open_nodes": 1, "generated_columns": 0, "cuts": 0, "pricing_calls": 0, "pricing_time_seconds": 0, "rmp_solve_time_seconds": 0, "relaxation_time_seconds": 29.9870616, "lower_bound_source": "gamma_floor", "lower_bound_sources": "gamma_floor"}
  ],
  "branch_price_nodes": [
    {"node_id": 0, "parent_id": -1, "tree_node_sequence": 1, "depth": 0, "branch_restrictions": "root", "lp_rmp_objective": 0.0456319724868, "inherited_lower_bound": 0.0122881381662, "best_node_lower_bound": 0.0456319724868, "cg_iterations": 1, "active_columns": 4620, "cuts": 0, "branching_decision": "none", "pricing_closed": false, "not_closed_reason": "pricing_did_not_close", "outcome": "unresolved"}
  ],
  "pricing_calls": [
    {"iteration": 0, "vehicle": 0, "event": "pricing_time_limit", "dual_summary": "visit_l1=0.00663707265379;operation_l1=0.0313965924462;vehicle_constant=0.0539192229709", "pricing_engine_requested": "exact-label", "pricing_engine_used": "exact-label", "reused_capacity_price": false, "generated_columns": 6731919, "returned_negative_columns": 0, "route_states": 5889756054, "operation_states": 33333198866, "labels_pruned_support_duration": 0, "labels_pruned_completion_lb": 0, "labels_pruned_required_closure": 0, "label_dominance_comparisons": 0, "labels_pruned_label_dominance": 0, "labels_pruned_cross_pickup_dominance": 0, "label_dominance_inactive_entries_skipped": 0, "label_dominance_bucket_compactions": 0, "label_dominance_compacted_entries": 0, "operation_dp_dominance_pruned_states": 4696761045, "pricing_label_dominance_mode": "safe", "pricing_label_dominance_exact_safe": true, "pricing_completion_bound_mode": "basic", "pricing_decomposition": "auto", "pricing_load_dp_cache_enabled": false, "pricing_route_skeleton_mode": "standard", "pricing_route_skeleton_cache_enabled": false, "pricing_operation_dp_dominance_enabled": true, "pricing_load_dp_dominance_enabled": true, "pricing_labels_generated": 5889756054, "pricing_labels_kept": 0, "pricing_labels_expanded": 5889756054, "pricing_labels_pruned_duration": 16122354457, "pricing_labels_pruned_load": 0, "pricing_labels_pruned_station": 0, "pricing_labels_pruned_support": 0, "pricing_labels_pruned_reduced_cost": 0, "pricing_labels_pruned_dominance": 0, "pricing_labels_duplicate_states": 0, "pricing_state_stop_reason": "negative_columns_remaining", "pricing_depth_profile": [{"depth":1,"labels_generated":1,"labels_kept":0,"labels_expanded":1,"pruned_duration":0,"pruned_load":0,"pruned_station":0,"pruned_support":0,"pruned_reduced_cost":0,"pruned_dominance":0,"duplicate_states":0,"operation_states_generated":1,"operation_states_pruned":0,"columns_generated":1,"negative_columns_found":0,"best_reduced_cost":0.00171268278898},{"depth":2,"labels_generated":1,"labels_kept":0,"labels_expanded":1,"pruned_duration":0,"pruned_load":0,"pruned_station":0,"pruned_support":0,"pruned_reduced_cost":0,"pruned_dominance":0,"duplicate_states":0,"operation_states_generated":12,"operation_states_pruned":0,"columns_generated":1,"negative_columns_found":1,"best_reduced_cost":-0.00263957260261},{"depth":3,"labels_generated":1,"labels_kept":0,"labels_expanded":1,"pruned_duration":0,"pruned_load":0,"pruned_station":0,"pruned_support":0,"pruned_reduced_cost":0,"pruned_dominance":0,"duplicate_states":0,"operation_states_generated":32,"operation_states_pruned":54,"columns_generated":1,"negative_columns_found":1,"best_reduced_cost":-0.0490140420973},{"depth":4,"labels_generated":2,"labels_kept":0,"labels_expanded":2,"pruned_duration":0,"pruned_load":0,"pruned_station":0,"pruned_support":0,"pruned_reduced_cost":0,"pruned_dominance":0,"duplicate_states":0,"operation_states_generated":357,"operation_states_pruned":108,"columns_generated":2,"negative_columns_found":2,"best_reduced_cost":-0.0433004343895},{"depth":5,"labels_generated":26,"labels_kept":0,"labels_expanded":26,"pruned_duration":0,"pruned_load":0,"pruned_station":0,"pruned_support":0,"pruned_reduced_cost":0,"pruned_dominance":0,"duplicate_states":0,"operation_states_generated":5827,"operation_states_pruned":1376,"columns_generated":26,"negative_columns_found":26,"best_reduced_cost":-0.0510854648853},{"depth":6,"labels_generated":379,"labels_kept":0,"labels_expanded":379,"pruned_duration":0,"pruned_load":0,"pruned_station":0,"pruned_support":0,"pruned_reduced_cost":0,"pruned_dominance":0,"duplicate_states":0,"operation_states_generated":78856,"operation_states_pruned":16764,"columns_generated":379,"negative_columns_found":379,"best_reduced_cost":-0.0520983477517},{"depth":7,"labels_generated":5297,"labels_kept":0,"labels_expanded":5297,"pruned_duration":0,"pruned_load":0,"pruned_station":0,"pruned_support":0,"pruned_reduced_cost":0,"pruned_dominance":0,"duplicate_states":0,"operation_states_generated":839610,"operation_states_pruned":158237,"columns_generated":4990,"negative_columns_found":4980,"best_reduced_cost":-0.0507967815303},{"depth":8,"labels_generated":66868,"labels_kept":0,"labels_expanded":66868,"pruned_duration":1987,"pruned_load":0,"pruned_station":0,"pruned_support":0,"pruned_reduced_cost":0,"pruned_dominance":0,"duplicate_states":0,"operation_states_generated":6597377,"operation_states_pruned":1127516,"columns_generated":45976,"negative_columns_found":44768,"best_reduced_cost":-0.0491907341243},{"depth":9,"labels_generated":657328,"labels_kept":0,"labels_expanded":657328,"pruned_duration":145079,"pruned_load":0,"pruned_station":0,"pruned_support":0,"pruned_reduced_cost":0,"pruned_dominance":0,"duplicate_states":0,"operation_states_generated":37915679,"operation_states_pruned":6077389,"columns_generated":218340,"negative_columns_found":216553,"best_reduced_cost":-0.0464833250918},{"depth":10,"labels_generated":4703153,"labels_kept":0,"labels_expanded":4703153,"pruned_duration":2527451,"pruned_load":0,"pruned_station":0,"pruned_support":0,"pruned_reduced_cost":0,"pruned_dominance":0,"duplicate_states":0,"operation_states_generated":161715677,"operation_states_pruned":25096650,"columns_generated":908975,"negative_columns_found":868131,"best_reduced_cost":-0.0411999498631},{"depth":11,"labels_generated":24518362,"labels_kept":0,"labels_expanded":24518362,"pruned_duration":22513159,"pruned_load":0,"pruned_station":0,"pruned_support":0,"pruned_reduced_cost":0,"pruned_dominance":0,"duplicate_states":0,"operation_states_generated":528352888,"operation_states_pruned":80794152,"columns_generated":1403791,"negative_columns_found":1388933,"best_reduced_cost":-0.0355718760436},{"depth":12,"labels_generated":94033674,"labels_kept":0,"labels_expanded":94033674,"pruned_duration":126631576,"pruned_load":0,"pruned_station":0,"pruned_support":0,"pruned_reduced_cost":0,"pruned_dominance":0,"duplicate_states":0,"operation_states_generated":1351278989,"operation_states_pruned":206366510,"columns_generated":2664377,"negative_columns_found":2487480,"best_reduced_cost":-0.0339658286375},{"depth":13,"labels_generated":267508202,"labels_kept":0,"labels_expanded":267508202,"pruned_duration":484761185,"pruned_load":0,"pruned_station":0,"pruned_support":0,"pruned_reduced_cost":0,"pruned_dominance":0,"duplicate_states":0,"operation_states_generated":2763075824,"operation_states_pruned":423394095,"columns_generated":839010,"negative_columns_found":838381,"best_reduced_cost":-0.0300241909432},{"depth":14,"labels_generated":572555881,"labels_kept":0,"labels_expanded":572555881,"pruned_duration":1300001531,"pruned_load":0,"pruned_station":0,"pruned_support":0,"pruned_reduced_cost":0,"pruned_dominance":0,"duplicate_states":0,"operation_states_generated":4574488568,"operation_states_pruned":700928481,"columns_generated":574217,"negative_columns_found":569003,"best_reduced_cost":-0.0284181435371},{"depth":15,"labels_generated":943239981,"labels_kept":0,"labels_expanded":943239981,"pruned_duration":2492095300,"pruned_load":0,"pruned_station":0,"pruned_support":0,"pruned_reduced_cost":0,"pruned_dominance":0,"duplicate_states":0,"operation_states_generated":6187148649,"operation_states_pruned":932663867,"columns_generated":71833,"negative_columns_found":71833,"best_reduced_cost":-0.0185970925097},{"depth":16,"labels_generated":1222012273,"labels_kept":0,"labels_expanded":1222012273,"pruned_duration":3494187628,"pruned_load":0,"pruned_station":0,"pruned_support":0,"pruned_reduced_cost":0,"pruned_dominance":0,"duplicate_states":0,"operation_states_generated":6789006352,"operation_states_pruned":978382482,"columns_generated":0,"negative_columns_found":0,"best_reduced_cost":null},{"depth":17,"labels_generated":1241555031,"labels_kept":0,"labels_expanded":1241555031,"pruned_duration":3646494059,"pruned_load":0,"pruned_station":0,"pruned_support":0,"pruned_reduced_cost":0,"pruned_dominance":0,"duplicate_states":0,"operation_states_generated":5805119620,"operation_states_pruned":771240100,"columns_generated":0,"negative_columns_found":0,"best_reduced_cost":null},{"depth":18,"labels_generated":939857583,"labels_kept":0,"labels_expanded":939857583,"pruned_duration":2784807510,"pruned_load":0,"pruned_station":0,"pruned_support":0,"pruned_reduced_cost":0,"pruned_dominance":0,"duplicate_states":0,"operation_states_generated":3543213260,"operation_states_pruned":417105456,"columns_generated":0,"negative_columns_found":0,"best_reduced_cost":null},{"depth":19,"labels_generated":467514837,"labels_kept":0,"labels_expanded":467514837,"pruned_duration":1412200329,"pruned_load":0,"pruned_station":0,"pruned_support":0,"pruned_reduced_cost":0,"pruned_dominance":0,"duplicate_states":0,"operation_states_generated":1348571636,"operation_states_pruned":134551762,"columns_generated":0,"negative_columns_found":0,"best_reduced_cost":null},{"depth":20,"labels_generated":111527174,"labels_kept":0,"labels_expanded":111527174,"pruned_duration":355987663,"pruned_load":0,"pruned_station":0,"pruned_support":0,"pruned_reduced_cost":0,"pruned_dominance":0,"duplicate_states":0,"operation_states_generated":235789652,"operation_states_pruned":18856046,"columns_generated":0,"negative_columns_found":0,"best_reduced_cost":null}], "operation_dp_profile": [{"depth":1,"operation_states_generated":1,"operation_states_pruned":0},{"depth":2,"operation_states_generated":12,"operation_states_pruned":0},{"depth":3,"operation_states_generated":32,"operation_states_pruned":54},{"depth":4,"operation_states_generated":357,"operation_states_pruned":108},{"depth":5,"operation_states_generated":5827,"operation_states_pruned":1376},{"depth":6,"operation_states_generated":78856,"operation_states_pruned":16764},{"depth":7,"operation_states_generated":839610,"operation_states_pruned":158237},{"depth":8,"operation_states_generated":6597377,"operation_states_pruned":1127516},{"depth":9,"operation_states_generated":37915679,"operation_states_pruned":6077389},{"depth":10,"operation_states_generated":161715677,"operation_states_pruned":25096650},{"depth":11,"operation_states_generated":528352888,"operation_states_pruned":80794152},{"depth":12,"operation_states_generated":1351278989,"operation_states_pruned":206366510},{"depth":13,"operation_states_generated":2763075824,"operation_states_pruned":423394095},{"depth":14,"operation_states_generated":4574488568,"operation_states_pruned":700928481},{"depth":15,"operation_states_generated":6187148649,"operation_states_pruned":932663867},{"depth":16,"operation_states_generated":6789006352,"operation_states_pruned":978382482},{"depth":17,"operation_states_generated":5805119620,"operation_states_pruned":771240100},{"depth":18,"operation_states_generated":3543213260,"operation_states_pruned":417105456},{"depth":19,"operation_states_generated":1348571636,"operation_states_pruned":134551762},{"depth":20,"operation_states_generated":235789652,"operation_states_pruned":18856046}], "best_reduced_cost": 0.00182087521921, "exact_completed": false, "early_negative_stop": false, "time_seconds": 9204.003921, "timeout_unfinished_state_count": 39222954920},
    {"node_id": 0, "parent_id": -1, "tree_node_sequence": 1, "depth": 0, "node_pricing_call": 0, "pricing_call": {"iteration": 0, "vehicle": 0, "event": "pricing_time_limit", "dual_summary": "visit_l1=0.00663707265379;operation_l1=0.0313965924462;vehicle_constant=0.0539192229709", "pricing_engine_requested": "exact-label", "pricing_engine_used": "exact-label", "reused_capacity_price": false, "generated_columns": 6731919, "returned_negative_columns": 0, "route_states": 5889756054, "operation_states": 33333198866, "labels_pruned_support_duration": 0, "labels_pruned_completion_lb": 0, "labels_pruned_required_closure": 0, "label_dominance_comparisons": 0, "labels_pruned_label_dominance": 0, "labels_pruned_cross_pickup_dominance": 0, "label_dominance_inactive_entries_skipped": 0, "label_dominance_bucket_compactions": 0, "label_dominance_compacted_entries": 0, "operation_dp_dominance_pruned_states": 4696761045, "pricing_label_dominance_mode": "safe", "pricing_label_dominance_exact_safe": true, "pricing_completion_bound_mode": "basic", "pricing_decomposition": "auto", "pricing_load_dp_cache_enabled": false, "pricing_route_skeleton_mode": "standard", "pricing_route_skeleton_cache_enabled": false, "pricing_operation_dp_dominance_enabled": true, "pricing_load_dp_dominance_enabled": true, "pricing_labels_generated": 5889756054, "pricing_labels_kept": 0, "pricing_labels_expanded": 5889756054, "pricing_labels_pruned_duration": 16122354457, "pricing_labels_pruned_load": 0, "pricing_labels_pruned_station": 0, "pricing_labels_pruned_support": 0, "pricing_labels_pruned_reduced_cost": 0, "pricing_labels_pruned_dominance": 0, "pricing_labels_duplicate_states": 0, "pricing_state_stop_reason": "negative_columns_remaining", "pricing_depth_profile": [{"depth":1,"labels_generated":1,"labels_kept":0,"labels_expanded":1,"pruned_duration":0,"pruned_load":0,"pruned_station":0,"pruned_support":0,"pruned_reduced_cost":0,"pruned_dominance":0,"duplicate_states":0,"operation_states_generated":1,"operation_states_pruned":0,"columns_generated":1,"negative_columns_found":0,"best_reduced_cost":0.00171268278898},{"depth":2,"labels_generated":1,"labels_kept":0,"labels_expanded":1,"pruned_duration":0,"pruned_load":0,"pruned_station":0,"pruned_support":0,"pruned_reduced_cost":0,"pruned_dominance":0,"duplicate_states":0,"operation_states_generated":12,"operation_states_pruned":0,"columns_generated":1,"negative_columns_found":1,"best_reduced_cost":-0.00263957260261},{"depth":3,"labels_generated":1,"labels_kept":0,"labels_expanded":1,"pruned_duration":0,"pruned_load":0,"pruned_station":0,"pruned_support":0,"pruned_reduced_cost":0,"pruned_dominance":0,"duplicate_states":0,"operation_states_generated":32,"operation_states_pruned":54,"columns_generated":1,"negative_columns_found":1,"best_reduced_cost":-0.0490140420973},{"depth":4,"labels_generated":2,"labels_kept":0,"labels_expanded":2,"pruned_duration":0,"pruned_load":0,"pruned_station":0,"pruned_support":0,"pruned_reduced_cost":0,"pruned_dominance":0,"duplicate_states":0,"operation_states_generated":357,"operation_states_pruned":108,"columns_generated":2,"negative_columns_found":2,"best_reduced_cost":-0.0433004343895},{"depth":5,"labels_generated":26,"labels_kept":0,"labels_expanded":26,"pruned_duration":0,"pruned_load":0,"pruned_station":0,"pruned_support":0,"pruned_reduced_cost":0,"pruned_dominance":0,"duplicate_states":0,"operation_states_generated":5827,"operation_states_pruned":1376,"columns_generated":26,"negative_columns_found":26,"best_reduced_cost":-0.0510854648853},{"depth":6,"labels_generated":379,"labels_kept":0,"labels_expanded":379,"pruned_duration":0,"pruned_load":0,"pruned_station":0,"pruned_support":0,"pruned_reduced_cost":0,"pruned_dominance":0,"duplicate_states":0,"operation_states_generated":78856,"operation_states_pruned":16764,"columns_generated":379,"negative_columns_found":379,"best_reduced_cost":-0.0520983477517},{"depth":7,"labels_generated":5297,"labels_kept":0,"labels_expanded":5297,"pruned_duration":0,"pruned_load":0,"pruned_station":0,"pruned_support":0,"pruned_reduced_cost":0,"pruned_dominance":0,"duplicate_states":0,"operation_states_generated":839610,"operation_states_pruned":158237,"columns_generated":4990,"negative_columns_found":4980,"best_reduced_cost":-0.0507967815303},{"depth":8,"labels_generated":66868,"labels_kept":0,"labels_expanded":66868,"pruned_duration":1987,"pruned_load":0,"pruned_station":0,"pruned_support":0,"pruned_reduced_cost":0,"pruned_dominance":0,"duplicate_states":0,"operation_states_generated":6597377,"operation_states_pruned":1127516,"columns_generated":45976,"negative_columns_found":44768,"best_reduced_cost":-0.0491907341243},{"depth":9,"labels_generated":657328,"labels_kept":0,"labels_expanded":657328,"pruned_duration":145079,"pruned_load":0,"pruned_station":0,"pruned_support":0,"pruned_reduced_cost":0,"pruned_dominance":0,"duplicate_states":0,"operation_states_generated":37915679,"operation_states_pruned":6077389,"columns_generated":218340,"negative_columns_found":216553,"best_reduced_cost":-0.0464833250918},{"depth":10,"labels_generated":4703153,"labels_kept":0,"labels_expanded":4703153,"pruned_duration":2527451,"pruned_load":0,"pruned_station":0,"pruned_support":0,"pruned_reduced_cost":0,"pruned_dominance":0,"duplicate_states":0,"operation_states_generated":161715677,"operation_states_pruned":25096650,"columns_generated":908975,"negative_columns_found":868131,"best_reduced_cost":-0.0411999498631},{"depth":11,"labels_generated":24518362,"labels_kept":0,"labels_expanded":24518362,"pruned_duration":22513159,"pruned_load":0,"pruned_station":0,"pruned_support":0,"pruned_reduced_cost":0,"pruned_dominance":0,"duplicate_states":0,"operation_states_generated":528352888,"operation_states_pruned":80794152,"columns_generated":1403791,"negative_columns_found":1388933,"best_reduced_cost":-0.0355718760436},{"depth":12,"labels_generated":94033674,"labels_kept":0,"labels_expanded":94033674,"pruned_duration":126631576,"pruned_load":0,"pruned_station":0,"pruned_support":0,"pruned_reduced_cost":0,"pruned_dominance":0,"duplicate_states":0,"operation_states_generated":1351278989,"operation_states_pruned":206366510,"columns_generated":2664377,"negative_columns_found":2487480,"best_reduced_cost":-0.0339658286375},{"depth":13,"labels_generated":267508202,"labels_kept":0,"labels_expanded":267508202,"pruned_duration":484761185,"pruned_load":0,"pruned_station":0,"pruned_support":0,"pruned_reduced_cost":0,"pruned_dominance":0,"duplicate_states":0,"operation_states_generated":2763075824,"operation_states_pruned":423394095,"columns_generated":839010,"negative_columns_found":838381,"best_reduced_cost":-0.0300241909432},{"depth":14,"labels_generated":572555881,"labels_kept":0,"labels_expanded":572555881,"pruned_duration":1300001531,"pruned_load":0,"pruned_station":0,"pruned_support":0,"pruned_reduced_cost":0,"pruned_dominance":0,"duplicate_states":0,"operation_states_generated":4574488568,"operation_states_pruned":700928481,"columns_generated":574217,"negative_columns_found":569003,"best_reduced_cost":-0.0284181435371},{"depth":15,"labels_generated":943239981,"labels_kept":0,"labels_expanded":943239981,"pruned_duration":2492095300,"pruned_load":0,"pruned_station":0,"pruned_support":0,"pruned_reduced_cost":0,"pruned_dominance":0,"duplicate_states":0,"operation_states_generated":6187148649,"operation_states_pruned":932663867,"columns_generated":71833,"negative_columns_found":71833,"best_reduced_cost":-0.0185970925097},{"depth":16,"labels_generated":1222012273,"labels_kept":0,"labels_expanded":1222012273,"pruned_duration":3494187628,"pruned_load":0,"pruned_station":0,"pruned_support":0,"pruned_reduced_cost":0,"pruned_dominance":0,"duplicate_states":0,"operation_states_generated":6789006352,"operation_states_pruned":978382482,"columns_generated":0,"negative_columns_found":0,"best_reduced_cost":null},{"depth":17,"labels_generated":1241555031,"labels_kept":0,"labels_expanded":1241555031,"pruned_duration":3646494059,"pruned_load":0,"pruned_station":0,"pruned_support":0,"pruned_reduced_cost":0,"pruned_dominance":0,"duplicate_states":0,"operation_states_generated":5805119620,"operation_states_pruned":771240100,"columns_generated":0,"negative_columns_found":0,"best_reduced_cost":null},{"depth":18,"labels_generated":939857583,"labels_kept":0,"labels_expanded":939857583,"pruned_duration":2784807510,"pruned_load":0,"pruned_station":0,"pruned_support":0,"pruned_reduced_cost":0,"pruned_dominance":0,"duplicate_states":0,"operation_states_generated":3543213260,"operation_states_pruned":417105456,"columns_generated":0,"negative_columns_found":0,"best_reduced_cost":null},{"depth":19,"labels_generated":467514837,"labels_kept":0,"labels_expanded":467514837,"pruned_duration":1412200329,"pruned_load":0,"pruned_station":0,"pruned_support":0,"pruned_reduced_cost":0,"pruned_dominance":0,"duplicate_states":0,"operation_states_generated":1348571636,"operation_states_pruned":134551762,"columns_generated":0,"negative_columns_found":0,"best_reduced_cost":null},{"depth":20,"labels_generated":111527174,"labels_kept":0,"labels_expanded":111527174,"pruned_duration":355987663,"pruned_load":0,"pruned_station":0,"pruned_support":0,"pruned_reduced_cost":0,"pruned_dominance":0,"duplicate_states":0,"operation_states_generated":235789652,"operation_states_pruned":18856046,"columns_generated":0,"negative_columns_found":0,"best_reduced_cost":null}], "operation_dp_profile": [{"depth":1,"operation_states_generated":1,"operation_states_pruned":0},{"depth":2,"operation_states_generated":12,"operation_states_pruned":0},{"depth":3,"operation_states_generated":32,"operation_states_pruned":54},{"depth":4,"operation_states_generated":357,"operation_states_pruned":108},{"depth":5,"operation_states_generated":5827,"operation_states_pruned":1376},{"depth":6,"operation_states_generated":78856,"operation_states_pruned":16764},{"depth":7,"operation_states_generated":839610,"operation_states_pruned":158237},{"depth":8,"operation_states_generated":6597377,"operation_states_pruned":1127516},{"depth":9,"operation_states_generated":37915679,"operation_states_pruned":6077389},{"depth":10,"operation_states_generated":161715677,"operation_states_pruned":25096650},{"depth":11,"operation_states_generated":528352888,"operation_states_pruned":80794152},{"depth":12,"operation_states_generated":1351278989,"operation_states_pruned":206366510},{"depth":13,"operation_states_generated":2763075824,"operation_states_pruned":423394095},{"depth":14,"operation_states_generated":4574488568,"operation_states_pruned":700928481},{"depth":15,"operation_states_generated":6187148649,"operation_states_pruned":932663867},{"depth":16,"operation_states_generated":6789006352,"operation_states_pruned":978382482},{"depth":17,"operation_states_generated":5805119620,"operation_states_pruned":771240100},{"depth":18,"operation_states_generated":3543213260,"operation_states_pruned":417105456},{"depth":19,"operation_states_generated":1348571636,"operation_states_pruned":134551762},{"depth":20,"operation_states_generated":235789652,"operation_states_pruned":18856046}], "best_reduced_cost": 0.00182087521921, "exact_completed": false, "early_negative_stop": false, "time_seconds": 9204.003921, "timeout_unfinished_state_count": 39222954920}}
  ]
}
