{
    "audit_date":  "2026-06-14",
    "scope":  "certified target-result artifacts used in portfolio discussion",
    "entries":  [
                    {
                        "label":  "V10_M2_average_BPC",
                        "file":  "results\\dyn4_v10_m2_average_frontier_routemask_relax20_refine18_1200s.json",
                        "instance":  "test_data_V10_M2_average.txt",
                        "method":  "gcap-frontier",
                        "method_scope":  "original_bpc",
                        "certificate_type":  "full_gini_frontier_route_load_bpc",
                        "status":  "optimal",
                        "objective":  0.463263009179,
                        "lower_bound":  0.463263009179,
                        "upper_bound":  0.463263009179,
                        "gap":  0,
                        "runtime_seconds":  589.0030151,
                        "verifier_passed":  true,
                        "certified_original_problem":  true,
                        "audit_certified":  true,
                        "conditions":  {
                                           "status_optimal":  true,
                                           "gap_zero":  true,
                                           "lb_eq_obj":  true,
                                           "ub_eq_obj":  true,
                                           "verifier_passed":  true,
                                           "scope_matches":  true,
                                           "solves_original_objective":  true,
                                           "bpc_frontier_closed":  true
                                       },
                        "frontier_summary":  "frontier certification summary: closed_intervals=0, bound_certified_intervals=48, skipped_intervals=0, unresolved_intervals=0, invalid_bound_intervals=0, final_full_objective_range=true"
                    },
                    {
                        "label":  "V10_M1_average_BPC",
                        "file":  "results\\closure3600_v10_m1_average_strong_bpcseed.json",
                        "instance":  "test_data_V10_M1_average.txt",
                        "method":  "gcap-frontier",
                        "method_scope":  "original_bpc",
                        "certificate_type":  "full_gini_frontier_route_load_bpc",
                        "status":  "optimal",
                        "objective":  0.49262512358,
                        "lower_bound":  0.49262512358,
                        "upper_bound":  0.49262512358,
                        "gap":  0,
                        "runtime_seconds":  641.0843535,
                        "verifier_passed":  true,
                        "certified_original_problem":  true,
                        "audit_certified":  true,
                        "conditions":  {
                                           "status_optimal":  true,
                                           "gap_zero":  true,
                                           "lb_eq_obj":  true,
                                           "ub_eq_obj":  true,
                                           "verifier_passed":  true,
                                           "scope_matches":  true,
                                           "solves_original_objective":  true,
                                           "bpc_frontier_closed":  true
                                       },
                        "frontier_summary":  "frontier certification summary: closed_intervals=1, bound_certified_intervals=43, skipped_intervals=0, unresolved_intervals=0, invalid_bound_intervals=0, final_full_objective_range=true"
                    },
                    {
                        "label":  "V12_M1_average_BPC",
                        "file":  "results\\closure7200_v12_m1_average_strong_bpcseed.json",
                        "instance":  "test_data_V12_M1_average.txt",
                        "method":  "gcap-frontier",
                        "method_scope":  "original_bpc",
                        "certificate_type":  "full_gini_frontier_route_load_bpc",
                        "status":  "optimal",
                        "objective":  0.690938574743,
                        "lower_bound":  0.690938574743,
                        "upper_bound":  0.690938574743,
                        "gap":  0,
                        "runtime_seconds":  5280.7002047,
                        "verifier_passed":  true,
                        "certified_original_problem":  true,
                        "audit_certified":  true,
                        "conditions":  {
                                           "status_optimal":  true,
                                           "gap_zero":  true,
                                           "lb_eq_obj":  true,
                                           "ub_eq_obj":  true,
                                           "verifier_passed":  true,
                                           "scope_matches":  true,
                                           "solves_original_objective":  true,
                                           "bpc_frontier_closed":  true
                                       },
                        "frontier_summary":  "frontier certification summary: closed_intervals=0, bound_certified_intervals=72, skipped_intervals=0, unresolved_intervals=0, invalid_bound_intervals=0, final_full_objective_range=true"
                    },
                    {
                        "label":  "V10_M1_average_compact",
                        "file":  "results\\alt_strengthened_v10_m1_average_300s.json",
                        "instance":  "test_data_V10_M1_average.txt",
                        "method":  "cplex",
                        "method_scope":  "original_compact",
                        "certificate_type":  "strengthened_compact_cplex_mip",
                        "status":  "optimal",
                        "objective":  0.49262512358,
                        "lower_bound":  0.49262512358,
                        "upper_bound":  0.49262512358,
                        "gap":  0,
                        "runtime_seconds":  166.3435737,
                        "verifier_passed":  true,
                        "certified_original_problem":  true,
                        "audit_certified":  true,
                        "conditions":  {
                                           "status_optimal":  true,
                                           "gap_zero":  true,
                                           "lb_eq_obj":  true,
                                           "ub_eq_obj":  true,
                                           "verifier_passed":  true,
                                           "scope_matches":  true,
                                           "solves_original_objective":  true,
                                           "bpc_frontier_closed":  true
                                       },
                        "frontier_summary":  ""
                    },
                    {
                        "label":  "V10_M2_low_compact",
                        "file":  "results\\alt_strengthened_v10_m2_low_1200s.json",
                        "instance":  "test_data_V10_M2_low.txt",
                        "method":  "cplex",
                        "method_scope":  "original_compact",
                        "certificate_type":  "strengthened_compact_cplex_mip",
                        "status":  "optimal",
                        "objective":  0.824301313135,
                        "lower_bound":  0.824301313135,
                        "upper_bound":  0.824301313135,
                        "gap":  0,
                        "runtime_seconds":  938.1947592,
                        "verifier_passed":  true,
                        "certified_original_problem":  true,
                        "audit_certified":  true,
                        "conditions":  {
                                           "status_optimal":  true,
                                           "gap_zero":  true,
                                           "lb_eq_obj":  true,
                                           "ub_eq_obj":  true,
                                           "verifier_passed":  true,
                                           "scope_matches":  true,
                                           "solves_original_objective":  true,
                                           "bpc_frontier_closed":  true
                                       },
                        "frontier_summary":  ""
                    },
                    {
                        "label":  "V12_M1_average_compact",
                        "file":  "results\\alt_strengthened_v12_m1_average_300s.json",
                        "instance":  "test_data_V12_M1_average.txt",
                        "method":  "cplex",
                        "method_scope":  "original_compact",
                        "certificate_type":  "strengthened_compact_cplex_mip",
                        "status":  "optimal",
                        "objective":  0.690938574743,
                        "lower_bound":  0.690938574743,
                        "upper_bound":  0.690938574743,
                        "gap":  0,
                        "runtime_seconds":  123.3197084,
                        "verifier_passed":  true,
                        "certified_original_problem":  true,
                        "audit_certified":  true,
                        "conditions":  {
                                           "status_optimal":  true,
                                           "gap_zero":  true,
                                           "lb_eq_obj":  true,
                                           "ub_eq_obj":  true,
                                           "verifier_passed":  true,
                                           "scope_matches":  true,
                                           "solves_original_objective":  true,
                                           "bpc_frontier_closed":  true
                                       },
                        "frontier_summary":  ""
                    },
                    {
                        "label":  "V10_M1_average_plain_cplex",
                        "file":  "results\\current2_cplex_v10_m1_average_plain_300s.json",
                        "instance":  "test_data_V10_M1_average.txt",
                        "method":  "cplex",
                        "method_scope":  "plain_cplex",
                        "certificate_type":  "plain_cplex_compact_mip",
                        "status":  "optimal",
                        "objective":  0.49262512358,
                        "lower_bound":  0.49262512358,
                        "upper_bound":  0.49262512358,
                        "gap":  0,
                        "runtime_seconds":  63.317532,
                        "verifier_passed":  true,
                        "certified_original_problem":  true,
                        "audit_certified":  true,
                        "conditions":  {
                                           "status_optimal":  true,
                                           "gap_zero":  true,
                                           "lb_eq_obj":  true,
                                           "ub_eq_obj":  true,
                                           "verifier_passed":  true,
                                           "scope_matches":  true,
                                           "solves_original_objective":  true,
                                           "bpc_frontier_closed":  true
                                       },
                        "frontier_summary":  ""
                    },
                    {
                        "label":  "V12_M1_average_plain_cplex",
                        "file":  "results\\current2_cplex_v12_m1_average_plain_300s.json",
                        "instance":  "test_data_V12_M1_average.txt",
                        "method":  "cplex",
                        "method_scope":  "plain_cplex",
                        "certificate_type":  "plain_cplex_compact_mip",
                        "status":  "optimal",
                        "objective":  0.690938574743,
                        "lower_bound":  0.690938574743,
                        "upper_bound":  0.690938574743,
                        "gap":  0,
                        "runtime_seconds":  9.2283908,
                        "verifier_passed":  true,
                        "certified_original_problem":  true,
                        "audit_certified":  true,
                        "conditions":  {
                                           "status_optimal":  true,
                                           "gap_zero":  true,
                                           "lb_eq_obj":  true,
                                           "ub_eq_obj":  true,
                                           "verifier_passed":  true,
                                           "scope_matches":  true,
                                           "solves_original_objective":  true,
                                           "bpc_frontier_closed":  true
                                       },
                        "frontier_summary":  ""
                    }
                ]
}
