{
    "audit_date":  "2026-06-14",
    "result_file":  "results\\closure7200_v12_m1_average_strong_bpcseed.json",
    "stdout_file":  "logs\\closure7200_v12_m1_average_strong_bpcseed.stdout.txt",
    "stderr_file":  "logs\\closure7200_v12_m1_average_strong_bpcseed.stderr.txt",
    "declared_log_file":  "logs\\closure7200_v12_m1_average_strong_bpcseed.log",
    "declared_log_file_exists":  false,
    "artifact_warning":  "Declared log_file is missing; stdout/stderr and JSON notes were audited instead.",
    "method":  "gcap-frontier",
    "method_scope":  "original_bpc",
    "solves_original_objective":  true,
    "is_bpc":  true,
    "certificate_type":  "full_gini_frontier_route_load_bpc",
    "status":  "optimal",
    "objective":  0.690938574743,
    "lower_bound":  0.690938574743,
    "upper_bound":  0.690938574743,
    "gap":  0,
    "runtime_seconds":  5280.7002047,
    "verifier_passed":  true,
    "certified_original_problem":  true,
    "unresolved_intervals":  0,
    "invalid_bound_intervals":  0,
    "open_nodes":  0,
    "nodes":  17891,
    "columns":  8838,
    "pricing_calls":  75,
    "pricing_closed_nodes":  20,
    "conditions":  {
                       "method_is_gcap_frontier":  true,
                       "method_scope_original_bpc":  true,
                       "solves_original_objective":  true,
                       "is_bpc":  true,
                       "status_optimal":  true,
                       "objective_matches_expected":  true,
                       "lower_equals_objective":  true,
                       "upper_equals_objective":  true,
                       "gap_zero":  true,
                       "verifier_passed":  true,
                       "unresolved_intervals_zero":  true,
                       "invalid_bound_intervals_zero":  true,
                       "top_level_open_nodes_zero":  true,
                       "full_frontier_coverage_evidence":  true,
                       "proof_not_restricted_pool":  true,
                       "not_compact_fallback":  true
                   },
    "audit_certified":  true,
    "incumbent_note":  "adaptive frontier pass 1 found improved incumbent in interval 116, objective=0.690939",
    "retry_note":  "adaptive pass 1 retry 1 interval 116 [0.47045,0.47045] complete=false, lower_bound_valid=true, certified_by_bound=true, empty_interval=false, has_incumbent=true, tree_lb=0.690939, interval_lb=0.690939, inventory_relax_lb=0.690939, resource_lb=0.171452, incumbent_cutoff=0.690939, early_stop_target=0.690939, nodes=15, columns=4988, pricing_calls=64, pricing_time=708.875, master_time=1456.25, bound_time=0, cuts_added=0, open_nodes=6",
    "frontier_summary_note":  "frontier certification summary: closed_intervals=0, bound_certified_intervals=72, skipped_intervals=0, unresolved_intervals=0, invalid_bound_intervals=0, final_full_objective_range=true",
    "proof_comment":  "The final retry note contains complete=false and open_nodes=6, but that incomplete branch-price tree is not used as a closed tree certificate. It found an improved incumbent and the interval/frontier ledger is then certified by valid bounds at the new incumbent cutoff. The top-level result has open_nodes=0 and unresolved_intervals=0.",
    "conclusion":  "Certified pure full Gini-frontier route-load BPC optimum for the original EBRP objective. Not compact fallback, not CPLEX-warmed diagnostic, and not restricted-pool optimality."
}
